{
	"configurations" : 
	[
		{
			"directories" : 
			[
				{
					"build" : ".",
					"jsonFile" : "directory-.-Debug-f5ebdc15457944623624.json",
					"projectIndex" : 0,
					"source" : ".",
					"targetIndexes" : 
					[
						0,
						1,
						2,
						3,
						4,
						5,
						6,
						7,
						8,
						9
					]
				}
			],
			"name" : "Debug",
			"projects" : 
			[
				{
					"directoryIndexes" : 
					[
						0
					],
					"name" : "libnetco",
					"targetIndexes" : 
					[
						0,
						1,
						2,
						3,
						4,
						5,
						6,
						7,
						8,
						9
					]
				}
			],
			"targets" : 
			[
				{
					"directoryIndex" : 0,
					"id" : "doubly_buffer_test::@6890427a1f51a3e7e1df",
					"jsonFile" : "target-doubly_buffer_test-Debug-a1197cfcc58df35fb556.json",
					"name" : "doubly_buffer_test",
					"projectIndex" : 0
				},
				{
					"directoryIndex" : 0,
					"id" : "libnetco::@6890427a1f51a3e7e1df",
					"jsonFile" : "target-libnetco-Debug-bb1b97bf13cf91377bfc.json",
					"name" : "libnetco",
					"projectIndex" : 0
				},
				{
					"directoryIndex" : 0,
					"id" : "log_test::@6890427a1f51a3e7e1df",
					"jsonFile" : "target-log_test-Debug-9ebd5225e3ae63cfbbd6.json",
					"name" : "log_test",
					"projectIndex" : 0
				},
				{
					"directoryIndex" : 0,
					"id" : "method_test::@6890427a1f51a3e7e1df",
					"jsonFile" : "target-method_test-Debug-76b2cbebd9c006b44a48.json",
					"name" : "method_test",
					"projectIndex" : 0
				},
				{
					"directoryIndex" : 0,
					"id" : "name_service_test::@6890427a1f51a3e7e1df",
					"jsonFile" : "target-name_service_test-Debug-336f91e44131501376c4.json",
					"name" : "name_service_test",
					"projectIndex" : 0
				},
				{
					"directoryIndex" : 0,
					"id" : "rpc_client_pb_test::@6890427a1f51a3e7e1df",
					"jsonFile" : "target-rpc_client_pb_test-Debug-ac172b2ac53a5c976cdf.json",
					"name" : "rpc_client_pb_test",
					"projectIndex" : 0
				},
				{
					"directoryIndex" : 0,
					"id" : "rpc_server_pb_test::@6890427a1f51a3e7e1df",
					"jsonFile" : "target-rpc_server_pb_test-Debug-1bae264cc3dd083b7ae8.json",
					"name" : "rpc_server_pb_test",
					"projectIndex" : 0
				},
				{
					"directoryIndex" : 0,
					"id" : "tcp_client_test::@6890427a1f51a3e7e1df",
					"jsonFile" : "target-tcp_client_test-Debug-0fbab57a23be73f98909.json",
					"name" : "tcp_client_test",
					"projectIndex" : 0
				},
				{
					"directoryIndex" : 0,
					"id" : "tcp_server_test::@6890427a1f51a3e7e1df",
					"jsonFile" : "target-tcp_server_test-Debug-b88317d8b65864aa1f04.json",
					"name" : "tcp_server_test",
					"projectIndex" : 0
				},
				{
					"directoryIndex" : 0,
					"id" : "zkTest::@6890427a1f51a3e7e1df",
					"jsonFile" : "target-zkTest-Debug-c13e6a53b8ee2ccf52d3.json",
					"name" : "zkTest",
					"projectIndex" : 0
				}
			]
		}
	],
	"kind" : "codemodel",
	"paths" : 
	{
		"build" : "/home/bob/libNetCo/build",
		"source" : "/home/bob/libNetCo"
	},
	"version" : 
	{
		"major" : 2,
		"minor" : 3
	}
}
